pycv2/__init__.py
pycv2/PIL/TextDrawer.py
pycv2/PIL/__init__.py
pycv2/PIL/utils.py
pycv2/detector/__init__.py
pycv2/detector/face_landmarks.py
pycv2/detector/facedetect.py
pycv2/detector/hand.py
pycv2/detector/pose.py
pycv2/img/__init__.py
pycv2/img/conv_pdf.py
pycv2/img/roate_img.py
pycv2/img/textread.py
pycv2/img/utils.py
pycv2/img/drawing/__init__.py
pycv2/img/drawing/box.py
pycv2/img/poppler-0.68.0/bin/AUTHORS
pycv2/img/poppler-0.68.0/bin/BINARIES
pycv2/img/poppler-0.68.0/bin/COPYING
pycv2/img/poppler-0.68.0/bin/COPYING3
pycv2/img/poppler-0.68.0/bin/README
pycv2/img/poppler-0.68.0/bin/README-XPDF
pycv2/img/poppler-0.68.0/bin/freetype6.dll
pycv2/img/poppler-0.68.0/bin/jpeg62.dll
pycv2/img/poppler-0.68.0/bin/libcairo-2.dll
pycv2/img/poppler-0.68.0/bin/libexpat-1.dll
pycv2/img/poppler-0.68.0/bin/libfontconfig-1.dll
pycv2/img/poppler-0.68.0/bin/libgcc_s_dw2-1.dll
pycv2/img/poppler-0.68.0/bin/libpixman-1-0.dll
pycv2/img/poppler-0.68.0/bin/libpng16-16.dll
pycv2/img/poppler-0.68.0/bin/libpoppler-79.dll
pycv2/img/poppler-0.68.0/bin/libpoppler-cpp-0.dll
pycv2/img/poppler-0.68.0/bin/libstdc++-6.dll
pycv2/img/poppler-0.68.0/bin/libtiff3.dll
pycv2/img/poppler-0.68.0/bin/pdfdetach.exe
pycv2/img/poppler-0.68.0/bin/pdffonts.exe
pycv2/img/poppler-0.68.0/bin/pdfimages.exe
pycv2/img/poppler-0.68.0/bin/pdfinfo.exe
pycv2/img/poppler-0.68.0/bin/pdfseparate.exe
pycv2/img/poppler-0.68.0/bin/pdftocairo.exe
pycv2/img/poppler-0.68.0/bin/pdftohtml.exe
pycv2/img/poppler-0.68.0/bin/pdftoppm.exe
pycv2/img/poppler-0.68.0/bin/pdftops.exe
pycv2/img/poppler-0.68.0/bin/pdftotext.exe
pycv2/img/poppler-0.68.0/bin/pdfunite.exe
pycv2/img/poppler-0.68.0/bin/zlib1.dll
pycv2/img/poppler-0.68.0/include/poppler/cpp/poppler-document.h
pycv2/img/poppler-0.68.0/include/poppler/cpp/poppler-embedded-file.h
pycv2/img/poppler-0.68.0/include/poppler/cpp/poppler-font.h
pycv2/img/poppler-0.68.0/include/poppler/cpp/poppler-global.h
pycv2/img/poppler-0.68.0/include/poppler/cpp/poppler-image.h
cv_imutils-0.0.1.4.dist-info/METADATA
cv_imutils-0.0.1.4.dist-info/WHEEL
cv_imutils-0.0.1.4.dist-info/top_level.txt
cv_imutils-0.0.1.4.dist-info/RECORD
