Metadata-Version: 2.1
Name: cv-imutils
Version: 0.0.1.4
Summary: Lightweight utility package for common computer vision tasks.
Home-page: UNKNOWN
Author: Emam_ahsour
Author-email: emam54637@gmail.com
License: UNKNOWN
Keywords: python,cv2-utils,tools,pycv2,cv2-functions,cv2-most-used functions
Platform: UNKNOWN
Classifier: Development Status :: 1 - Planning
Classifier: Intended Audience :: Developers
Classifier: Programming Language :: Python :: 3
Classifier: Operating System :: Unix
Classifier: Operating System :: MacOS :: MacOS X
Classifier: Operating System :: Microsoft :: Windows
